pwdata/__init__.py
pwdata/atomconfig.py
pwdata/configop.py
pwdata/cp2kdata.py
pwdata/datasets_saver.py
pwdata/dump.py
pwdata/extendedxyz.py
pwdata/image.py
pwdata/lammpsdata.py
pwdata/lmps.py
pwdata/main.py
pwdata/movement.py
pwdata/movement_saver.py
pwdata/outcar.py
pwdata/poscar.py
pwdata/build/__init__.py
pwdata/build/cell.py
pwdata/build/geometry.py
pwdata/build/supercells.py
pwdata/build/write_struc.py
pwdata/calculators/__init__.py
pwdata/calculators/const.py
pwdata/calculators/unitconvert_lmps.py
pwdata/calculators/units.py
pwdata/pertub/__init__.py
pwdata/pertub/perturbation.py
pwdata/pertub/scale.py
pwdata-2024.3.3.dist-info/LICENSE
pwdata-2024.3.3.dist-info/METADATA
pwdata-2024.3.3.dist-info/WHEEL
pwdata-2024.3.3.dist-info/top_level.txt
pwdata-2024.3.3.dist-info/RECORD
