Metadata-Version: 2.1
Name: pwdata
Version: 2024.3.3
Summary: pwdata is a data pre-processing tool for PWMLFF, which can be used to extract features and labels. It also provides convenient interfaces for data conversion between different software.
Home-page: https://github.com/LonxunQuantum/pwdata
Author: LonxunQuantum
Author-email: lonxun@pwmat.com
Classifier: Programming Language :: Python :: 3
Classifier: License :: OSI Approved :: GNU General Public License v3 (GPLv3)
Classifier: Operating System :: OS Independent
Requires-Python: >=3.9
License-File: LICENSE
